main.py
ghost_in_the_shell-0.1.7.dist-info/licenses/LICENSE.md
ghost_in_the_shell-0.1.7.dist-info/METADATA
ghost_in_the_shell-0.1.7.dist-info/WHEEL
ghost_in_the_shell-0.1.7.dist-info/entry_points.txt
ghost_in_the_shell-0.1.7.dist-info/top_level.txt
ghost_in_the_shell-0.1.7.dist-info/RECORD
