Metadata-Version: 2.4
Name: ghost-in-the-shell
Version: 0.1.7
Summary: CLI with OpenAI integration
Requires-Python: >=3.11
License-File: LICENSE.md
Requires-Dist: openai>=1.69.0
Requires-Dist: prompt_toolkit
Dynamic: license-file
